{
  "neutral": [
    { "id": "neutral-0", "path": "@/assets/face/neutral/1f610.png" },
    { "id": "neutral-1", "path": "@/assets/face/neutral/1f636.png" },
    { "id": "neutral-2", "path": "@/assets/face/neutral/1f611.png" }
  ],
  "smile": [
    { "id": "smile-0", "path": "@/assets/face/smile/smile1.gif" },
    { "id": "smile-1", "path": "@/assets/face/smile/smile2.gif" },
    { "id": "smile-2", "path": "@/assets/face/smile/smile3.gif" },
    { "id": "smile-3", "path": "@/assets/face/smile/smile4.gif" },
    { "id": "smile-4", "path": "@/assets/face/smile/smile5.gif" }
  ],
  "sad": [
    { "id": "sad-0", "path": "@/assets/face/sad/pleading_face.gif" },
    { "id": "sad-1", "path": "@/assets/face/sad/crying_face.gif" },
    { "id": "sad-2", "path": "@/assets/face/sad/weary_face.gif" },
    { "id": "sad-3", "path": "@/assets/face/sad/loudly_crying_face.gif" }
  ],
  "surprise": [
    { "id": "surprise-0", "path": "@/assets/face/surprise/surprised.gif" },
    { "id": "surprise-1", "path": "@/assets/face/surprise/hushed_face.gif" },
    { "id": "surprise-2", "path": "@/assets/face/surprise/flushed_face.gif" }
  ],
  "disgusted": [
    {
      "id": "disgusted-0",
      "path": "@/assets/face/disgusted/unamused_face.gif"
    },
    { "id": "disgusted-1", "path": "@/assets/face/disgusted/face_vomiting.gif" }
  ],
  "angry": [
    { "id": "angry-0", "path": "@/assets/face/angry/face_vomiting.gif" },
    {
      "id": "angry-1",
      "path": "@/assets/face/angry/face_with_steam_from_nose.gif"
    },
    {
      "id": "angry-2",
      "path": "@/assets/face/angry/face_with_symbols_on_mouth.gif"
    },
    { "id": "angry-3", "path": "@/assets/face/angry/exploding_head.gif" }
  ],
  "fearful": [
    {
      "id": "angry-0",
      "path": "@/assets/face/fearful/face_screaming_in_fear.gif"
    },
    { "id": "angry-0", "path": "@/assets/face/fearful/cold_face.gif" }
  ]
}
